gel_pydantic_codegen/__init__.py
gel_pydantic_codegen/__main__.py
gel_pydantic_codegen/generator.py
gel_pydantic_codegen/models.py
gel_pydantic_codegen/template.py.jinja
gel_pydantic_codegen/utils.py
gel_pydantic_codegen-1.1.0.dist-info/METADATA
gel_pydantic_codegen-1.1.0.dist-info/WHEEL
gel_pydantic_codegen-1.1.0.dist-info/entry_points.txt
gel_pydantic_codegen-1.1.0.dist-info/licenses/LICENSE
gel_pydantic_codegen-1.1.0.dist-info/RECORD
