Metadata-Version: 2.4
Name: gel-pydantic-codegen
Version: 1.1.0
Summary: Alternative Python Gel code generator (Pydantic V2 + asyncio, FastAPI compatible)
Project-URL: homepage, https://github.com/Japan7/gel-pydantic-codegen
Author-email: NextFire <git@yuru.moe>
License-Expression: MIT
License-File: LICENSE
Requires-Python: >=3.11
Requires-Dist: gel<4,>=3
Requires-Dist: jinja2<4,>=3
Requires-Dist: orjson<4,>=3
Requires-Dist: pydantic<3,>=2
Requires-Dist: ruff<1,>=0.1.2
